packsim/__init__.py
packsim/action.json
packsim/block.py
packsim/main.py
packsim/planning_time.json
packsim/task.py
packsim/test.py
packsim/tools.py
packsim/transform.py
packsim/.idea/RobotPackingBenchmark-main.iml
packsim/.idea/misc.xml
packsim/.idea/modules.xml
packsim/.idea/workspace.xml
packsim/.idea/inspectionProfiles/Project_Default.xml
packsim/.idea/inspectionProfiles/profiles_settings.xml
packsim/__pycache__/__init__.cpython-37.pyc
packsim/__pycache__/block.cpython-37.pyc
packsim/__pycache__/block.cpython-39.pyc
packsim/__pycache__/main.cpython-37.pyc
packsim/__pycache__/task.cpython-37.pyc
packsim/__pycache__/task.cpython-39.pyc
packsim/__pycache__/test.cpython-37.pyc
packsim/__pycache__/tools.cpython-37.pyc
packsim/__pycache__/transform.cpython-37.pyc
packsim/__pycache__/transform.cpython-39.pyc
packsim/arm_pybullet_env/debug_abb_robot.py
packsim/arm_pybullet_env/__pycache__/debug_abb_robot.cpython-37.pyc
packsim/arm_pybullet_env/arm_envs/__init__.py
packsim/arm_pybullet_env/arm_envs/arm.py
packsim/arm_pybullet_env/arm_envs/cameras.py
packsim/arm_pybullet_env/arm_envs/debug.py
packsim/arm_pybullet_env/arm_envs/envs.py
packsim/arm_pybullet_env/arm_envs/grippers.py
packsim/arm_pybullet_env/arm_envs/moma.py
packsim/arm_pybullet_env/arm_envs/pb_ompl.py
packsim/arm_pybullet_env/arm_envs/task.py
packsim/arm_pybullet_env/arm_envs/transform.py
packsim/arm_pybullet_env/arm_envs/__pycache__/__init__.cpython-37.pyc
packsim/arm_pybullet_env/arm_envs/__pycache__/arm.cpython-37.pyc
packsim/arm_pybullet_env/arm_envs/__pycache__/cameras.cpython-37.pyc
packsim/arm_pybullet_env/arm_envs/__pycache__/debug.cpython-37.pyc
packsim/arm_pybullet_env/arm_envs/__pycache__/envs.cpython-37.pyc
packsim/arm_pybullet_env/arm_envs/__pycache__/grippers.cpython-37.pyc
packsim/arm_pybullet_env/arm_envs/__pycache__/irb2400.cpython-37.pyc
packsim/arm_pybullet_env/arm_envs/__pycache__/irb6640.cpython-37.pyc
packsim/arm_pybullet_env/arm_envs/__pycache__/moma.cpython-37.pyc
packsim-0.0.4.dist-info/LICENSE
packsim-0.0.4.dist-info/METADATA
packsim-0.0.4.dist-info/WHEEL
packsim-0.0.4.dist-info/top_level.txt
packsim-0.0.4.dist-info/RECORD
